midas_smartnord/__init__.py
midas_smartnord/module.py
midas_sndata-2.0.0.dist-info/LICENSE
midas_sndata-2.0.0.dist-info/METADATA
midas_sndata-2.0.0.dist-info/WHEEL
midas_sndata-2.0.0.dist-info/top_level.txt
midas_sndata-2.0.0.dist-info/RECORD
