Metadata-Version: 2.1
Name: midas-sndata
Version: 2.0.0
Summary: A Midas module for the Smart Nord dataset.
Author-email: Stephan Balduin <stephan.balduin@offis.de>
Project-URL: Documentation, https://midas-mosaik.gitlab.io/midas
Requires-Python: >=3.8
License-File: LICENSE
Requires-Dist: midas_powerseries>=2.0.0
Requires-Dist: tables
Requires-Dist: pandas
Requires-Dist: numpy<2
